mimory_mcp_focus/__init__.py
mimory_mcp_focus/focus_client.py
mimory_mcp_focus-0.1.1.dist-info/METADATA
mimory_mcp_focus-0.1.1.dist-info/WHEEL
mimory_mcp_focus-0.1.1.dist-info/licenses/LICENSE
mimory_mcp_focus-0.1.1.dist-info/RECORD
