Metadata-Version: 2.4
Name: mimory-mcp-focus
Version: 0.1.1
Summary: Focus-enforcing wrapper for MCP Python clients (dict-based param and tool allowlists).
Project-URL: Homepage, https://github.com/MimoryInc/mimory-mcp-focus
Project-URL: Issues, https://github.com/MimoryInc/mimory-mcp-focus/issues
Author-email: Travis McQueen <oss@mimory.io>
License-Expression: MIT
License-File: LICENSE
Requires-Python: >=3.10
Requires-Dist: mcp>=1.14.0
Requires-Dist: pyjwt>=2.10.1
